unifyai_pii/__init__.py
unifyai_pii/api.py
unifyai_pii/loader.py
unifyai_pii/py.typed
unifyai_pii/registry.py
unifyai_pii/countries/__init__.py
unifyai_pii/countries/australia.py
unifyai_pii/countries/finland.py
unifyai_pii/countries/india.py
unifyai_pii/countries/italy.py
unifyai_pii/countries/poland.py
unifyai_pii/countries/singapore.py
unifyai_pii/countries/spain.py
unifyai_pii/countries/uk.py
unifyai_pii/countries/usa.py
unifyai_pii-0.1.0.dist-info/licenses/LICENSE
unifyai_pii-0.1.0.dist-info/METADATA
unifyai_pii-0.1.0.dist-info/WHEEL
unifyai_pii-0.1.0.dist-info/top_level.txt
unifyai_pii-0.1.0.dist-info/RECORD
