Metadata-Version: 2.4
Name: unifyai-pii
Version: 0.1.0
Summary: Country-specific PII recognizers for Microsoft Presidio
Author-email: Vivek Dalvi <vivekdalvi5143@gmail.com>
License: MIT
Project-URL: Homepage, https://github.com/Vivek5143/unifyai-pii
Project-URL: Documentation, https://github.com/Vivek5143/unifyai-pii#readme
Project-URL: Repository, https://github.com/Vivek5143/unifyai-pii
Project-URL: Issues, https://github.com/Vivek5143/unifyai-pii/issues
Keywords: presidio,pii,privacy,data-protection,nlp,country-specific
Classifier: Development Status :: 3 - Alpha
Classifier: Intended Audience :: Developers
Classifier: License :: OSI Approved :: MIT License
Classifier: Operating System :: OS Independent
Classifier: Programming Language :: Python :: 3
Classifier: Programming Language :: Python :: 3.9
Classifier: Programming Language :: Python :: 3.10
Classifier: Programming Language :: Python :: 3.11
Classifier: Programming Language :: Python :: 3.12
Classifier: Topic :: Software Development :: Libraries :: Python Modules
Classifier: Topic :: Security
Requires-Python: <4.0,>=3.9
License-File: LICENSE
Requires-Dist: presidio-analyzer>=2.2.0
Provides-Extra: dev
Requires-Dist: pytest>=7.0; extra == "dev"
Requires-Dist: pytest-cov>=4.0; extra == "dev"
Requires-Dist: ruff; extra == "dev"
Dynamic: license-file
